biomaj_zipkin/__init__.py
biomaj_zipkin/zipkin.py
biomaj_zipkin-0.2.2.dist-info/DESCRIPTION.rst
biomaj_zipkin-0.2.2.dist-info/METADATA
biomaj_zipkin-0.2.2.dist-info/RECORD
biomaj_zipkin-0.2.2.dist-info/WHEEL
biomaj_zipkin-0.2.2.dist-info/metadata.json
biomaj_zipkin-0.2.2.dist-info/top_level.txt
